ChangeLog
LICENSE
MANIFEST.in
README
setup.py
csp/__init__.py
csp/builtins.py
csp/csp.py
csp/dsp.py
csp/guards.py
csp/os_process.py
csp/os_thread.py
csp/patterns.py
csp/cchannels/CChannel.py
csp/cchannels/Channel.py
csp/cchannels/tests/commstime.py
csp/cchannels/tests/fulladder.py
csp/cchannels/tests/patterns.py
csp/cchannels/tests/simple.py
csp/cchannels/tests/tokenring.py
csp/lint/__init__.py
csp/lint/channels.py
csp/lint/lint.py
csp/lint/processes.py
csp/tracer/__init__.py
csp/tracer/cspmodel.py
csp/tracer/tracer.py
exstatic/__init__.py
exstatic/cspwarnings.py
exstatic/icode.py
exstatic/py2icode.py
exstatic/stack.py
exstatic/visitor.py
exstatic/warnings.py
python_csp.egg-info/PKG-INFO
python_csp.egg-info/SOURCES.txt
python_csp.egg-info/dependency_links.txt
python_csp.egg-info/entry_points.txt
python_csp.egg-info/top_level.txt
python_csp.egg-info/zip-safe
scripts/cspdb
scripts/csplint
scripts/python-csp
test/test_builtins.py
test/test_contexts.py
test/test_forever.py
test/test_tracer.py
test/testcsp.py
test/testpar.py
test/testrep.py
test/testsock.py