Metadata-Version: 1.0
Name: python-csp
Version: 0.1
Summary: Communicating sequential processes for Python
Home-page: http://code.google.com/p/python-csp/
Author: Sarah Mount
Author-email: s.mount@wlv.ac.uk
License: GPL
Keywords: concurrency multicore parallel
Platform: UNKNOWN
Classifier: Intended Audience :: Developers
Classifier: License :: OSI Approved :: GNU General Public License (GPL)
Classifier: Programming Language :: Python
Classifier: Topic :: Software Development :: Libraries
Classifier: Topic :: System :: Distributed Computing
